sequence_former/__init__.py
sequence_former/client.py
sequence_former/config.py
sequence_former/data_models.py
sequence_former/llm_processor.py
sequence_former/main.py
sequence_former/postprocessor.py
sequence_former/preprocessor.py
sequence_former/utils.py
sequence_former-0.1.2.dist-info/METADATA
sequence_former-0.1.2.dist-info/WHEEL
sequence_former-0.1.2.dist-info/entry_points.txt
sequence_former-0.1.2.dist-info/top_level.txt
sequence_former-0.1.2.dist-info/RECORD
