Metadata-Version: 2.4
Name: sequence-former
Version: 0.1.2
Summary: An intelligent, multi-modal document structuring engine powered by LLMs.
Author-email: IndenScale <hfu7565ytru@gmail.com>
Project-URL: Homepage, https://github.com/IndenScale/SequenceFormer
Project-URL: Bug Tracker, https://github.com/IndenScale/SequenceFormer/issues
Classifier: Programming Language :: Python :: 3
Classifier: License :: OSI Approved :: MIT License
Classifier: Operating System :: OS Independent
Classifier: Topic :: Text Processing
Classifier: Topic :: Scientific/Engineering :: Artificial Intelligence
Requires-Python: >=3.9
Requires-Dist: pydantic>=2.0
Requires-Dist: openai>=1.0
Requires-Dist: python-dotenv>=1.0
